thanhtungcalendar/Leaps.py
thanhtungcalendar/ListSearch.py
thanhtungcalendar/NewMoonGMT0.py
thanhtungcalendar/SolsticeGMT7.py
thanhtungcalendar/TsptCalendar.py
thanhtungcalendar/__init__.py
thanhtungcalendar/fortest.py
thanhtungcalendar-3.2.3.dist-info/LICENSE
thanhtungcalendar-3.2.3.dist-info/METADATA
thanhtungcalendar-3.2.3.dist-info/WHEEL
thanhtungcalendar-3.2.3.dist-info/top_level.txt
thanhtungcalendar-3.2.3.dist-info/RECORD
