Metadata-Version: 2.1
Name: thanhtungcalendar
Version: 3.2.3
Summary: A library for calculate calendar
Home-page: https://github.com/pypa/sampleproject
Author: Thanh Tung
Author-email: thanhtung247@gmail.com
Project-URL: Bug Tracker, https://github.com/pypa/sampleproject/issues
Classifier: Programming Language :: Python :: 3
Classifier: License :: OSI Approved :: MIT License
Classifier: Operating System :: OS Independent
Requires-Python: >=3.6
License-File: LICENSE
